{"v":"5.7.8","fr":30,"ip":0,"op":211,"w":300,"h":300,"nm":"free 01","ddd":0,"assets":[{"id":"comp_0","layers":[{"ddd":0,"ind":1,"ty":4,"nm":"Shield","sr":1,"ks":{"o":{"a":0,"k":100,"ix":11},"r":{"a":0,"k":14,"ix":10},"p":{"a":0,"k":[145.19,214.76,0],"ix":2,"l":2},"a":{"a":0,"k":[-125,218,0],"ix":1,"l":2},"s":{"a":0,"k":[100,100,100],"ix":6,"l":2}},"ao":0,"shapes":[{"ty":"gr","it":[{"ty":"gr","it":[{"ind":0,"ty":"sh","ix":1,"ks":{"a":0,"k":{"i":[[14.328,58.457],[0,0],[18.192,-4.457],[-6.204,-25.309],[31.537,-43.37]],"o":[[0,0],[0,0],[10.412,42.482],[8.604,35.106],[31.628,-20.282]],"v":[[-46.688,133.579],[-69.766,39.414],[-109.312,49.105],[-84.839,148.954],[-108.953,279.734]],"c":true},"ix":2},"nm":"Path 1","mn":"ADBE Vector Shape - Group","hd":false},{"ty":"fl","c":{"a":0,"k":[0.913725495338,0.929411768913,0.96862745285,1],"ix":4},"o":{"a":0,"k":100,"ix":5},"r":1,"bm":0,"nm":"Fill 1","mn":"ADBE Vector Graphic - Fill","hd":false},{"ty":"tr","p":{"a":0,"k":[0,0],"ix":2},"a":{"a":0,"k":[0,0],"ix":1},"s":{"a":0,"k":[100,100],"ix":3},"r":{"a":0,"k":0,"ix":6},"o":{"a":0,"k":100,"ix":7},"sk":{"a":0,"k":0,"ix":4},"sa":{"a":0,"k":0,"ix":5},"nm":"Transform"}],"nm":"Group 1","np":2,"cix":2,"bm":1,"ix":1,"mn":"ADBE Vector Group","hd":false},{"ty":"gr","it":[{"ty":"gr","it":[{"ind":0,"ty":"sh","ix":1,"ks":{"a":0,"k":{"i":[[19.15,-4.693],[18.38,11.144],[0,0],[0,0],[0,0],[0,0],[14.328,58.457],[0,0]],"o":[[-19.206,4.708],[0,0],[0,0],[0,0],[0,0],[31.628,-20.282],[0,0],[0,0]],"v":[[-116.038,50.752],[-168.398,37.186],[-163.786,57.434],[-148.141,121.358],[-111.259,271.447],[-108.953,279.734],[-46.688,133.579],[-69.766,39.414]],"c":true},"ix":2},"nm":"Path 1","mn":"ADBE Vector Shape - Group","hd":false},{"ty":"fl","c":{"a":0,"k":[0.815686285496,0.831372559071,0.964705884457,1],"ix":4},"o":{"a":0,"k":100,"ix":5},"r":1,"bm":0,"nm":"Fill 1","mn":"ADBE Vector Graphic - Fill","hd":false},{"ty":"tr","p":{"a":0,"k":[0,0],"ix":2},"a":{"a":0,"k":[0,0],"ix":1},"s":{"a":0,"k":[100,100],"ix":3},"r":{"a":0,"k":0,"ix":6},"o":{"a":0,"k":100,"ix":7},"sk":{"a":0,"k":0,"ix":4},"sa":{"a":0,"k":0,"ix":5},"nm":"Transform"}],"nm":"Group 1","np":2,"cix":2,"bm":0,"ix":1,"mn":"ADBE Vector Group","hd":false},{"ty":"gr","it":[{"ind":0,"ty":"sh","ix":1,"ks":{"a":0,"k":{"i":[[0.001,0.005],[19.751,-4.841],[0,0],[0,0],[-37.417,-3.355],[-0.001,0.003],[0,0]],"o":[[-10.395,17.147],[-18.012,4.415],[0,0],[14.327,58.458],[0,0],[0,0],[-0.001,-0.001]],"v":[[-168.404,37.18],[-208.56,73.429],[-254.824,84.768],[-231.746,178.934],[-108.956,279.736],[-108.953,279.734],[-168.398,37.186]],"c":true},"ix":2},"nm":"Path 1","mn":"ADBE Vector Shape - Group","hd":false},{"ty":"fl","c":{"a":0,"k":[0.913725495338,0.937254905701,1,1],"ix":4},"o":{"a":0,"k":100,"ix":5},"r":1,"bm":0,"nm":"Fill 1","mn":"ADBE Vector Graphic - Fill","hd":false},{"ty":"tr","p":{"a":0,"k":[0,0],"ix":2},"a":{"a":0,"k":[0,0],"ix":1},"s":{"a":0,"k":[100,100],"ix":3},"r":{"a":0,"k":0,"ix":6},"o":{"a":0,"k":100,"ix":7},"sk":{"a":0,"k":0,"ix":4},"sa":{"a":0,"k":0,"ix":5},"nm":"Transform"}],"nm":"Group 2","np":2,"cix":2,"bm":0,"ix":2,"mn":"ADBE Vector Group","hd":false},{"ty":"tr","p":{"a":0,"k":[0,0],"ix":2},"a":{"a":0,"k":[0,0],"ix":1},"s":{"a":0,"k":[100,100],"ix":3},"r":{"a":0,"k":0,"ix":6},"o":{"a":0,"k":100,"ix":7},"sk":{"a":0,"k":0,"ix":4},"sa":{"a":0,"k":0,"ix":5},"nm":"Transform"}],"nm":"Group 2","np":2,"cix":2,"bm":0,"ix":2,"mn":"ADBE Vector Group","hd":false},{"ty":"tr","p":{"a":0,"k":[-111,280],"ix":2},"a":{"a":0,"k":[-111,280],"ix":1},"s":{"a":0,"k":[100,100],"ix":3},"r":{"a":1,"k":[{"i":{"x":[0],"y":[1]},"o":{"x":[0.35],"y":[0]},"t":0,"s":[0]},{"i":{"x":[0],"y":[1]},"o":{"x":[0.35],"y":[0]},"t":150,"s":[0]},{"t":300,"s":[0]}],"ix":6},"o":{"a":0,"k":100,"ix":7},"sk":{"a":0,"k":0,"ix":4},"sa":{"a":0,"k":0,"ix":5},"nm":"Transform"}],"nm":"Group 3","np":2,"cix":2,"bm":1,"ix":1,"mn":"ADBE Vector Group","hd":false}],"ip":0,"op":301,"st":0,"bm":0}]}],"layers":[{"ddd":0,"ind":1,"ty":3,"nm":"Null 7","sr":1,"ks":{"o":{"a":0,"k":0,"ix":11},"r":{"a":0,"k":0,"ix":10},"p":{"a":0,"k":[-108,-364,0],"ix":2,"l":2},"a":{"a":0,"k":[0,0,0],"ix":1,"l":2},"s":{"a":0,"k":[100,100,100],"ix":6,"l":2}},"ao":0,"ip":0,"op":301,"st":0,"bm":0},{"ddd":0,"ind":2,"ty":0,"nm":"Shield Comp 6","td":1,"refId":"comp_0","sr":1,"ks":{"o":{"a":0,"k":100,"ix":11},"r":{"a":0,"k":0,"ix":10},"p":{"a":0,"k":[150,150,0],"ix":2,"l":2},"a":{"a":0,"k":[150,150,0],"ix":1,"l":2},"s":{"a":0,"k":[100,100,100],"ix":6,"l":2}},"ao":0,"w":300,"h":300,"ip":0,"op":301,"st":0,"bm":0},{"ddd":0,"ind":3,"ty":4,"nm":"Shape Layer 3","parent":1,"tt":1,"sr":1,"ks":{"o":{"a":0,"k":60,"ix":11},"r":{"a":0,"k":0,"ix":10},"p":{"a":1,"k":[{"i":{"x":0.833,"y":0.833},"o":{"x":0.167,"y":0.167},"t":10,"s":[215,362,0],"to":[58.667,0,0],"ti":[0,0,0]},{"t":38,"s":[567,362,0],"h":1},{"i":{"x":0.833,"y":0.833},"o":{"x":0.167,"y":0.167},"t":39,"s":[215,362,0],"to":[0,0,0],"ti":[0,0,0]},{"i":{"x":0.833,"y":0.833},"o":{"x":0.167,"y":0.167},"t":61,"s":[215,362,0],"to":[58.667,0,0],"ti":[0,0,0]},{"t":89,"s":[567,362,0],"h":1},{"i":{"x":0.833,"y":0.833},"o":{"x":0.167,"y":0.167},"t":90,"s":[215,362,0],"to":[0,0,0],"ti":[0,0,0]},{"i":{"x":0.833,"y":0.833},"o":{"x":0.167,"y":0.167},"t":121,"s":[215,362,0],"to":[58.667,0,0],"ti":[0,0,0]},{"t":149,"s":[567,362,0],"h":1},{"i":{"x":0.833,"y":0.833},"o":{"x":0.167,"y":0.167},"t":150,"s":[215,362,0],"to":[0,0,0],"ti":[0,0,0]},{"i":{"x":0.833,"y":0.833},"o":{"x":0.167,"y":0.167},"t":172,"s":[215,362,0],"to":[58.667,0,0],"ti":[0,0,0]},{"t":200,"s":[567,362,0],"h":1},{"t":201,"s":[215,362,0],"h":1}],"ix":2,"l":2},"a":{"a":0,"k":[0,0,0],"ix":1,"l":2},"s":{"a":0,"k":[100,100,100],"ix":6,"l":2}},"ao":0,"shapes":[{"ty":"gr","it":[{"ind":0,"ty":"sh","ix":1,"ks":{"a":0,"k":{"i":[[0,0],[0,0],[0,0],[0,0]],"o":[[0,0],[0,0],[0,0],[0,0]],"v":[[104.562,-191.001],[0.124,152.455],[-69.955,131.145],[34.483,-212.311]],"c":true},"ix":2},"nm":"Path 1","mn":"ADBE Vector Shape - Group","hd":false},{"ty":"fl","c":{"a":0,"k":[1,1,1,1],"ix":4},"o":{"a":0,"k":100,"ix":5},"r":1,"bm":0,"nm":"Fill 1","mn":"ADBE Vector Graphic - Fill","hd":false},{"ty":"tr","p":{"a":0,"k":[-170.5,173.5],"ix":2},"a":{"a":0,"k":[0,0],"ix":1},"s":{"a":0,"k":[100,100],"ix":3},"r":{"a":0,"k":0,"ix":6},"o":{"a":0,"k":100,"ix":7},"sk":{"a":0,"k":0,"ix":4},"sa":{"a":0,"k":0,"ix":5},"nm":"Transform"}],"nm":"Rectangle 1","np":2,"cix":2,"bm":0,"ix":1,"mn":"ADBE Vector Group","hd":false}],"ip":0,"op":301,"st":0,"bm":0},{"ddd":0,"ind":4,"ty":0,"nm":"Shield Comp 6","refId":"comp_0","sr":1,"ks":{"o":{"a":0,"k":100,"ix":11},"r":{"a":0,"k":0,"ix":10},"p":{"a":0,"k":[150,150,0],"ix":2,"l":2},"a":{"a":0,"k":[150,150,0],"ix":1,"l":2},"s":{"a":0,"k":[100,100,100],"ix":6,"l":2}},"ao":0,"w":300,"h":300,"ip":0,"op":301,"st":0,"bm":0},{"ddd":0,"ind":5,"ty":4,"nm":"react","sr":1,"ks":{"o":{"a":0,"k":100,"ix":11},"r":{"a":0,"k":14,"ix":10},"p":{"a":0,"k":[319.762,33.354,0],"ix":2,"l":2},"a":{"a":0,"k":[0,0,0],"ix":1,"l":2},"s":{"a":0,"k":[100,100,100],"ix":6,"l":2}},"ao":0,"shapes":[{"ty":"gr","it":[{"ty":"gr","it":[{"ind":0,"ty":"sh","ix":1,"ks":{"a":0,"k":{"i":[[19.15,-4.693],[18.38,11.144],[0,0],[14.328,58.457],[0,0]],"o":[[-19.206,4.708],[0,0],[31.628,-20.282],[0,0],[0,0]],"v":[[-116.038,50.752],[-168.398,37.186],[-108.953,279.734],[-46.688,133.579],[-69.766,39.414]],"c":true},"ix":2},"nm":"Path 2","mn":"ADBE Vector Shape - Group","hd":false},{"ind":1,"ty":"sh","ix":2,"ks":{"a":0,"k":{"i":[[0.001,0.005],[19.751,-4.841],[0,0],[0,0],[-37.417,-3.355],[-0.001,0.003],[0,0]],"o":[[-10.395,17.147],[-18.012,4.415],[0,0],[14.327,58.458],[0,0],[0,0],[-0.001,-0.001]],"v":[[-168.404,37.18],[-208.56,73.429],[-254.824,84.768],[-231.746,178.934],[-108.956,279.736],[-108.953,279.734],[-168.398,37.186]],"c":true},"ix":2},"nm":"Path 3","mn":"ADBE Vector Shape - Group","hd":false},{"ty":"tr","p":{"a":0,"k":[-111,280],"ix":2},"a":{"a":0,"k":[-111,280],"ix":1},"s":{"a":0,"k":[100,100],"ix":3},"r":{"a":0,"k":0,"ix":6},"o":{"a":0,"k":100,"ix":7},"sk":{"a":0,"k":0,"ix":4},"sa":{"a":0,"k":0,"ix":5},"nm":"Transform"}],"nm":"Group 2","np":2,"cix":2,"bm":0,"ix":1,"mn":"ADBE Vector Group","hd":false},{"ty":"st","c":{"a":0,"k":[0.324490576982,0.827450990677,0.537509202957,1],"ix":3},"o":{"a":1,"k":[{"i":{"x":[0.667],"y":[1]},"o":{"x":[0.333],"y":[0]},"t":1,"s":[67]},{"i":{"x":[0.667],"y":[1]},"o":{"x":[0.167],"y":[0]},"t":21,"s":[0]},{"i":{"x":[0.667],"y":[1]},"o":{"x":[0.167],"y":[0]},"t":102,"s":[0]},{"i":{"x":[0.667],"y":[1]},"o":{"x":[0.333],"y":[0]},"t":103,"s":[67]},{"t":123,"s":[0]}],"ix":4},"w":{"a":1,"k":[{"i":{"x":[0],"y":[1]},"o":{"x":[0.167],"y":[0.167]},"t":1,"s":[0]},{"i":{"x":[0.833],"y":[0.833]},"o":{"x":[0.167],"y":[0.167]},"t":59,"s":[54.861]},{"i":{"x":[0.833],"y":[0.833]},"o":{"x":[0.167],"y":[0.167]},"t":102,"s":[0]},{"i":{"x":[0],"y":[1]},"o":{"x":[0.167],"y":[0.167]},"t":103,"s":[0]},{"t":161,"s":[54.861]}],"ix":5},"lc":2,"lj":2,"bm":0,"nm":"Stroke 1","mn":"ADBE Vector Graphic - Stroke","hd":false},{"ty":"st","c":{"a":0,"k":[0.324490576982,0.827450990677,0.537509202957,1],"ix":3},"o":{"a":1,"k":[{"i":{"x":[0.667],"y":[1]},"o":{"x":[0.333],"y":[0]},"t":15,"s":[67]},{"i":{"x":[0.667],"y":[1]},"o":{"x":[0.167],"y":[0]},"t":35,"s":[0]},{"i":{"x":[0.833],"y":[1]},"o":{"x":[0.167],"y":[0]},"t":116,"s":[0]},{"i":{"x":[0.667],"y":[1]},"o":{"x":[0.333],"y":[0]},"t":117,"s":[67]},{"t":137,"s":[0]}],"ix":4},"w":{"a":1,"k":[{"i":{"x":[0],"y":[1]},"o":{"x":[0.167],"y":[0.167]},"t":15,"s":[0]},{"i":{"x":[0.833],"y":[0.833]},"o":{"x":[0.167],"y":[0.167]},"t":73,"s":[54.861]},{"i":{"x":[0.833],"y":[0.833]},"o":{"x":[0.167],"y":[0.167]},"t":116,"s":[0]},{"i":{"x":[0],"y":[1]},"o":{"x":[0.167],"y":[0.167]},"t":117,"s":[0]},{"t":175,"s":[54.861]}],"ix":5},"lc":2,"lj":2,"bm":0,"nm":"Stroke 2","mn":"ADBE Vector Graphic - Stroke","hd":false},{"ty":"st","c":{"a":0,"k":[0.324490576982,0.827450990677,0.537509202957,1],"ix":3},"o":{"a":1,"k":[{"i":{"x":[0.667],"y":[1]},"o":{"x":[0.333],"y":[0]},"t":49,"s":[67]},{"i":{"x":[0.667],"y":[1]},"o":{"x":[0.167],"y":[0]},"t":69,"s":[0]},{"i":{"x":[0.833],"y":[1]},"o":{"x":[0.167],"y":[0]},"t":150,"s":[0]},{"i":{"x":[0.667],"y":[1]},"o":{"x":[0.333],"y":[0]},"t":151,"s":[67]},{"t":171,"s":[0]}],"ix":4},"w":{"a":1,"k":[{"i":{"x":[0],"y":[1]},"o":{"x":[0.167],"y":[0.167]},"t":49,"s":[0]},{"i":{"x":[0.833],"y":[0.833]},"o":{"x":[0.167],"y":[0.167]},"t":107,"s":[54.861]},{"i":{"x":[0.833],"y":[0.833]},"o":{"x":[0.167],"y":[0.167]},"t":150,"s":[0]},{"i":{"x":[0],"y":[1]},"o":{"x":[0.167],"y":[0.167]},"t":151,"s":[0]},{"t":209,"s":[54.861]}],"ix":5},"lc":2,"lj":2,"bm":0,"nm":"Stroke 3","mn":"ADBE Vector Graphic - Stroke","hd":false},{"ty":"st","c":{"a":0,"k":[0.324490576982,0.827450990677,0.537509202957,1],"ix":3},"o":{"a":1,"k":[{"i":{"x":[0.667],"y":[1]},"o":{"x":[0.333],"y":[0]},"t":65,"s":[67]},{"i":{"x":[0.667],"y":[1]},"o":{"x":[0.167],"y":[0]},"t":85,"s":[0]},{"i":{"x":[0.833],"y":[1]},"o":{"x":[0.167],"y":[0]},"t":166,"s":[0]},{"i":{"x":[0.667],"y":[1]},"o":{"x":[0.333],"y":[0]},"t":167,"s":[67]},{"t":187,"s":[0]}],"ix":4},"w":{"a":1,"k":[{"i":{"x":[0],"y":[1]},"o":{"x":[0.167],"y":[0.167]},"t":65,"s":[0]},{"i":{"x":[0.833],"y":[0.833]},"o":{"x":[0.167],"y":[0.167]},"t":123,"s":[54.861]},{"i":{"x":[0.833],"y":[0.833]},"o":{"x":[0.167],"y":[0.167]},"t":166,"s":[0]},{"i":{"x":[0],"y":[1]},"o":{"x":[0.167],"y":[0.167]},"t":167,"s":[0]},{"t":225,"s":[54.861]}],"ix":5},"lc":2,"lj":2,"bm":0,"nm":"Stroke 4","mn":"ADBE Vector Graphic - Stroke","hd":false},{"ty":"tr","p":{"a":0,"k":[0,0],"ix":2},"a":{"a":0,"k":[0,0],"ix":1},"s":{"a":0,"k":[100,100],"ix":3},"r":{"a":0,"k":0,"ix":6},"o":{"a":0,"k":100,"ix":7},"sk":{"a":0,"k":0,"ix":4},"sa":{"a":0,"k":0,"ix":5},"nm":"Transform"}],"nm":"Group 3","np":5,"cix":2,"bm":0,"ix":1,"mn":"ADBE Vector Group","hd":false}],"ip":0,"op":301,"st":0,"bm":0}],"markers":[]}